MANIFEST.in
setup.cfg
setup.py
protlego/__init__.py
protlego/all.py
protlego/definitions.py
protlego.egg-info/PKG-INFO
protlego.egg-info/SOURCES.txt
protlego.egg-info/dependency_links.txt
protlego.egg-info/requires.txt
protlego.egg-info/top_level.txt
protlego/builder/AAcodes.py
protlego/builder/TMalign
protlego/builder/__init__.py
protlego/builder/alignments.py
protlego/builder/builder.py
protlego/builder/chimera.py
protlego/builder/__pycache__/AAcodes.cpython-36.pyc
protlego/builder/__pycache__/__init__.cpython-36.pyc
protlego/builder/__pycache__/alignments.cpython-36.pyc
protlego/builder/__pycache__/builder.cpython-36.pyc
protlego/builder/__pycache__/chimera.cpython-36.pyc
protlego/database/__init__.py
protlego/database/data.py
protlego/database/database_setup.py
protlego/database/__pycache__/__init__.cpython-36.pyc
protlego/database/__pycache__/data.cpython-36.pyc
protlego/docs/__init__.py
protlego/docs/building.ipynb
protlego/docs/conf.py
protlego/docs/energy.ipynb
protlego/docs/fetching.ipynb
protlego/docs/introduction.ipynb
protlego/docs/network.ipynb
protlego/docs/structural.ipynb
protlego/docs/.ipynb_checkpoints/building-checkpoint.ipynb
protlego/docs/.ipynb_checkpoints/energy-checkpoint.ipynb
protlego/docs/.ipynb_checkpoints/fetching-checkpoint.ipynb
protlego/docs/.ipynb_checkpoints/network-checkpoint.ipynb
protlego/docs/.ipynb_checkpoints/structural-checkpoint.ipynb
protlego/network/__init__.py
protlego/network/colors.py
protlego/network/networks.py
protlego/network/__pycache__/__init__.cpython-36.pyc
protlego/network/__pycache__/colors.cpython-36.pyc
protlego/network/__pycache__/networks.cpython-36.pyc
protlego/scorer/__init__.py
protlego/scorer/mm_energies.py
protlego/scorer/__pycache__/__init__.cpython-36.pyc
protlego/scorer/__pycache__/mm_energies.cpython-36.pyc
protlego/scorer/__pycache__/rosetta.cpython-36.pyc
protlego/structural/__init__.py
protlego/structural/analysis.py
protlego/structural/clusters.py
protlego/structural/hh_networks.py
protlego/structural/salt_bridges.py
protlego/structural/__pycache__/__init__.cpython-36.pyc
protlego/structural/__pycache__/analysestrc.cpython-36.pyc
